HiveNetLib/__init__.py
HiveNetLib/deps_tool.py
HiveNetLib/formula.py
HiveNetLib/generic.py
HiveNetLib/html_parser.py
HiveNetLib/pipeline.py
HiveNetLib/pipeline_router.py
HiveNetLib/prompt_plus.py
HiveNetLib/redirect_stdout.py
HiveNetLib/simple_cache.py
HiveNetLib/simple_i18n.py
HiveNetLib/simple_id.py
HiveNetLib/simple_log.py
HiveNetLib/simple_parallel.py
HiveNetLib/simple_queue.py
HiveNetLib/simple_server_fw.py
HiveNetLib/simple_stream.py
HiveNetLib/simple_webdriver.py
HiveNetLib/simple_xml.py
HiveNetLib/base_tools/__init__.py
HiveNetLib/base_tools/call_chain_tool.py
HiveNetLib/base_tools/debug_tool.py
HiveNetLib/base_tools/exception_tool.py
HiveNetLib/base_tools/file_tool.py
HiveNetLib/base_tools/import_tool.py
HiveNetLib/base_tools/myzipfile.py
HiveNetLib/base_tools/net_tool.py
HiveNetLib/base_tools/run_tool.py
HiveNetLib/base_tools/string_tool.py
HiveNetLib/base_tools/test_tool.py
HiveNetLib/base_tools/validate_tool.py
HiveNetLib/base_tools/value_tool.py
HiveNetLib/base_tools/wget.py
HiveNetLib/base_tools/affinity/__init__.py
HiveNetLib/connection_pool/__init__.py
HiveNetLib/connection_pool/pool_fw.py
HiveNetLib/hivenet_error_code/__init__.py
HiveNetLib/hivenet_error_code/errorcode_en.json
HiveNetLib/hivenet_error_code/errorcode_zh.json
HiveNetLib/hivenet_error_code/map_error_code.json
HiveNetLib/interface_tool/__init__.py
HiveNetLib/interface_tool/intf_msg_fw.py
HiveNetLib/interface_tool/msg_fw.py
HiveNetLib/interface_tool/msg_json.py
HiveNetLib/interface_tool/msg_xml.py
HiveNetLib/interface_tool/protocol_msg_http.py
HiveNetLib/net_service/__init__.py
HiveNetLib/net_service/http_service.py
HiveNetLib/net_service/net_service_fw.py
HiveNetLib/net_service/netservicefw_en.json
HiveNetLib/net_service/netservicefw_zh.json
HiveNetLib/net_service/tcpip_service.py
HiveNetLib/simple_console/__init__.py
HiveNetLib/simple_console/base_cmd.py
HiveNetLib/simple_console/server.py
HiveNetLib/simple_console/conf/__init__.py
HiveNetLib/simple_console/conf/config.xml
HiveNetLib-0.8.8.dist-info/LICENSE
HiveNetLib-0.8.8.dist-info/METADATA
HiveNetLib-0.8.8.dist-info/WHEEL
HiveNetLib-0.8.8.dist-info/top_level.txt
HiveNetLib-0.8.8.dist-info/RECORD
