Metadata-Version: 2.1
Name: HiveNetLib
Version: 0.8.8
Summary: 一个方便开发人员调用的，集合一些常用开发功能的开发Python库.
Home-page: https://github.com/snakeclub/HiveNetLib
Author: 黎慧剑
Author-email: snakeclub@163.com
Maintainer: 黎慧剑
Maintainer-email: snakeclub@163.com
License: Mozilla Public License 2.0
Keywords: HiveNet development lib
Platform: all
Classifier: Operating System :: OS Independent
Classifier: License :: OSI Approved :: Mozilla Public License 2.0 (MPL 2.0)
Classifier: Programming Language :: Python :: 3.6
Classifier: Topic :: Software Development :: Libraries
Requires-Dist: gevent
Requires-Dist: eventlet
Requires-Dist: prompt-toolkit (>=2.0.0)
Requires-Dist: affinity (>=0.1.0)
Requires-Dist: dicttoxml (>=1.7.4)
Requires-Dist: grpcio (>=1.21.1)
Requires-Dist: grpcio-health-checking (>=1.21.1)
Requires-Dist: lxml
Requires-Dist: elementpath
Requires-Dist: googleapis-common-protos
Requires-Dist: jsonpath-rw
Requires-Dist: netifaces (>=0.10.9)
Requires-Dist: chardet
Requires-Dist: selenium
Requires-Dist: flask-cors
Requires-Dist: flask
Requires-Dist: flask-restful
Requires-Dist: flask-httpauth
Requires-Dist: flask-socketio
Requires-Dist: werkzeug
Requires-Dist: requests
Requires-Dist: pycryptodomex
